kubernetes_backend/__init__.py
kubernetes_backend/admin.py
kubernetes_backend/client.py
kubernetes_backend/manager.py
kubernetes_backend/models.py
kubernetes_backend/queryset.py
django_kubernetes_backend-0.1.2.dist-info/LICENSE
django_kubernetes_backend-0.1.2.dist-info/METADATA
django_kubernetes_backend-0.1.2.dist-info/WHEEL
django_kubernetes_backend-0.1.2.dist-info/RECORD
