Metadata-Version: 2.3
Name: django-kubernetes-backend
Version: 0.1.2
Summary: 
Author: Taylor Mitchell
Requires-Python: >=3.13
Classifier: Programming Language :: Python :: 3
Classifier: Programming Language :: Python :: 3.13
Requires-Dist: django (>=5.1.7,<6.0.0)
Requires-Dist: kubernetes (>=32.0.1,<33.0.0)
